geopackage_validator/__init__.py
geopackage_validator/cli.py
geopackage_validator/constants.py
geopackage_validator/generate.py
geopackage_validator/models.py
geopackage_validator/output.py
geopackage_validator/s3.py
geopackage_validator/utils.py
geopackage_validator/validate.py
geopackage_validator/validations/__init__.py
geopackage_validator/validations/attribute_table_check.py
geopackage_validator/validations/columnname_check.py
geopackage_validator/validations/db_views_check.py
geopackage_validator/validations/feature_id_check.py
geopackage_validator/validations/geom_column_check.py
geopackage_validator/validations/geometry_ccw_check.py
geopackage_validator/validations/geometry_dimension_check.py
geopackage_validator/validations/geometry_empty_check.py
geopackage_validator/validations/geometry_type_check.py
geopackage_validator/validations/geometry_valid_check.py
geopackage_validator/validations/layerfeature_check.py
geopackage_validator/validations/layername_check.py
geopackage_validator/validations/name_length_check.py
geopackage_validator/validations/rtree_present_check.py
geopackage_validator/validations/rtree_valid_check.py
geopackage_validator/validations/srs_check.py
geopackage_validator/validations/table_definitions_check.py
geopackage_validator/validations/validator.py
pdok_geopackage_validator-0.14.4.dist-info/licenses/LICENSE
pdok_geopackage_validator-0.14.4.dist-info/METADATA
pdok_geopackage_validator-0.14.4.dist-info/WHEEL
pdok_geopackage_validator-0.14.4.dist-info/entry_points.txt
pdok_geopackage_validator-0.14.4.dist-info/top_level.txt
pdok_geopackage_validator-0.14.4.dist-info/RECORD
