Metadata-Version: 2.4
Name: pdok-geopackage-validator
Version: 0.14.4
Summary: Validate Geopackage files according to PDOK requirements and recommendations
License: MIT
Keywords: geopackage-validator,geopackage,pdok
Classifier: Programming Language :: Python :: 3
Classifier: Programming Language :: Python :: 3 :: Only
Classifier: Programming Language :: Python :: 3.8
Classifier: Programming Language :: Python :: 3.9
Classifier: Programming Language :: Python :: 3.10
Classifier: Programming Language :: Python :: 3.11
Requires-Python: >=3.6
License-File: LICENSE
Requires-Dist: setuptools!=58.*,!=59.*,!=60.*,!=61.*,>=42.0
Requires-Dist: Click>=8.0
Requires-Dist: click-log>=0.3
Requires-Dist: gdal>=3.4
Requires-Dist: minio
Requires-Dist: pydantic>=2.9
Requires-Dist: pyyaml
Requires-Dist: semver>=3.0.2
Provides-Extra: test
Requires-Dist: black==22.3.0; extra == "test"
Requires-Dist: flake8; extra == "test"
Requires-Dist: ipdb; extra == "test"
Requires-Dist: ipython; extra == "test"
Requires-Dist: pytest>=7.0.1; extra == "test"
Requires-Dist: pytest-cov; extra == "test"
Requires-Dist: pytest-flakes; extra == "test"
Requires-Dist: pytest-mock; extra == "test"
Dynamic: license-file
